odamnet/CTD_functions.py
odamnet/WP_functions.py
odamnet/__init__.py
odamnet/customClick.py
odamnet/methods_functions.py
odamnet/odamnet.py
ODAMNet-1.1.0.dist-info/LICENSE
ODAMNet-1.1.0.dist-info/METADATA
ODAMNet-1.1.0.dist-info/WHEEL
ODAMNet-1.1.0.dist-info/entry_points.txt
ODAMNet-1.1.0.dist-info/top_level.txt
ODAMNet-1.1.0.dist-info/RECORD
