Metadata-Version: 2.1
Name: ODAMNet
Version: 1.1.0
Summary: Study molecular relationships between chemicals and rare diseases
Author: Morgane Térézol
License: MIT License
Project-URL: Source, https://github.com/MOohTus/ODAMNet
Project-URL: Documentation, https://odamnet.readthedocs.io/en/latest/
Keywords: rare diseases,overlap,WikiPathways,chemicals,pathways overlap,pathways diffusion,active module identification,random walk with restart,RWR,AMI,EJP-RD
Classifier: Programming Language :: Python :: 3.9
Classifier: Programming Language :: Python :: 3
Classifier: License :: OSI Approved :: MIT License
Classifier: Operating System :: POSIX :: Linux
Classifier: Environment :: Console
Requires-Python: >=3.9
License-File: LICENSE
Requires-Dist: requests (>=2.27.1)
Requires-Dist: SPARQLWrapper (>=1.8.5)
Requires-Dist: pandas (>=1.3.5)
Requires-Dist: scipy (>=1.7.3)
Requires-Dist: statsmodels (>=0.13.2)
Requires-Dist: alive-progress (>=2.4.1)
Requires-Dist: click-option-group (>=0.5.3)
Requires-Dist: click (>=8.0.1)
Requires-Dist: sphinx-tabs (>=3.4.1)
Requires-Dist: multixrank (==0.1)
Requires-Dist: ndex2 (==3.5.0)
Requires-Dist: networkx (==2.5)
